CHANGELOG.rst
LICENSE
README.rst
docs/api.rst
docs/conf.py
docs/index.rst
examples/__init__.py
examples/example.ini
examples/example.mako
examples/sqlalchemy.py
pyramid_resourceful/__init__.py
pyramid_resourceful/config.py
pyramid_resourceful/cors.py
pyramid_resourceful/renderers.py
pyramid_resourceful/resource.py
pyramid_resourceful/response.py
pyramid_resourceful/settings.py
pyramid_resourceful/sqlalchemy.py
pyramid_resourceful/util.py
pyramid_resourceful/view.py
pyramid_resourceful-1.0a2.dist-info/LICENSE
pyramid_resourceful-1.0a2.dist-info/WHEEL
pyramid_resourceful-1.0a2.dist-info/METADATA
pyramid_resourceful-1.0a2.dist-info/RECORD
